h_transport_materials/__init__.py
h_transport_materials/_version.py
h_transport_materials/fitting.py
h_transport_materials/plotting.py
h_transport_materials/properties_group.py
h_transport_materials/property.py
h_transport_materials/materials/__init__.py
h_transport_materials/materials/copper.py
h_transport_materials/materials/cucrzr.py
h_transport_materials/materials/material.py
h_transport_materials/materials/tungsten.py
tests/__init__.py
tests/test_arhenius_property.py
tests/test_fitting.py
tests/test_plotting.py
tests/test_properties_group.py
h_transport_properties-0.0.1.dist-info/LICENSE
h_transport_properties-0.0.1.dist-info/METADATA
h_transport_properties-0.0.1.dist-info/WHEEL
h_transport_properties-0.0.1.dist-info/top_level.txt
h_transport_properties-0.0.1.dist-info/RECORD
