Metadata-Version: 2.1
Name: h-transport-properties
Version: 0.0.1
Summary: Handle H transport properties
Home-page: https://github.com/RemDelaporteMathurin/h_transport_materials
Author: Remi Delaporte-Mathurin
Author-email: rdelaportemathurin@gmail.com
License: MIT
Project-URL: Source, https://github.com/RemDelaporteMathurin/h_transport_materials
Project-URL: Tracker, https://github.com/RemDelaporteMathurin/h_transport_materials/issues
Classifier: Natural Language :: English
Classifier: Topic :: Scientific/Engineering
Classifier: Programming Language :: Python :: 3
Classifier: Programming Language :: Python :: 3.6
Classifier: Programming Language :: Python :: 3.7
Classifier: Programming Language :: Python :: 3.8
Classifier: Programming Language :: Python :: 3.9
Classifier: Programming Language :: Python :: 3.10
Classifier: License :: OSI Approved :: MIT License
Classifier: Operating System :: OS Independent
Requires-Python: >=3.6
License-File: LICENSE
Requires-Dist: numpy (>=1.9)
Requires-Dist: matplotlib (>=3.2.2)
Requires-Dist: scipy (>=1.8)
Provides-Extra: tests
Requires-Dist: pytest (>=5.4.3) ; extra == 'tests'
